scrapyjs/__init__.py
scrapyjs/cache.py
scrapyjs/dupefilter.py
scrapyjs/middleware.py
scrapyjs/request.py
scrapyjs/utils.py
scrapyjs-0.2.dist-info/DESCRIPTION.rst
scrapyjs-0.2.dist-info/METADATA
scrapyjs-0.2.dist-info/RECORD
scrapyjs-0.2.dist-info/WHEEL
scrapyjs-0.2.dist-info/metadata.json
scrapyjs-0.2.dist-info/pbr.json
scrapyjs-0.2.dist-info/top_level.txt
